{
  "id": "G_REC",
  "title": "G_REC",
  "sourceGrp": "C:\\Users\\Administrator\\Desktop\\Multimedialny świat Juliana Tuwima PL\\Tuwim\\DATA\\G_REC.GRP",
  "cursors": [
    {
      "index": 0,
      "name": "action1",
      "width": 28,
      "height": 30,
      "url": "assets/cursors/G_REC_000.png",
      "path": "extracted_assets\\grp\\G_REC\\cursor_00_action1.pgm",
      "previewPath": "web_port\\assets\\cursors\\G_REC_000.png"
    },
    {
      "index": 1,
      "name": "up1",
      "width": 28,
      "height": 30,
      "url": "assets/cursors/G_REC_001.png",
      "path": "extracted_assets\\grp\\G_REC\\cursor_01_up1.pgm",
      "previewPath": "web_port\\assets\\cursors\\G_REC_001.png"
    },
    {
      "index": 2,
      "name": "down1",
      "width": 28,
      "height": 30,
      "url": "assets/cursors/G_REC_002.png",
      "path": "extracted_assets\\grp\\G_REC\\cursor_02_down1.pgm",
      "previewPath": "web_port\\assets\\cursors\\G_REC_002.png"
    },
    {
      "index": 3,
      "name": "sluchaj",
      "width": 28,
      "height": 30,
      "url": "assets/cursors/G_REC_003.png",
      "path": "extracted_assets\\grp\\G_REC\\cursor_03_sluchaj.pgm",
      "previewPath": "web_port\\assets\\cursors\\G_REC_003.png"
    },
    {
      "index": 4,
      "name": "tu_nie",
      "width": 28,
      "height": 30,
      "url": "assets/cursors/G_REC_004.png",
      "path": "extracted_assets\\grp\\G_REC\\cursor_04_tu_nie.pgm",
      "previewPath": "web_port\\assets\\cursors\\G_REC_004.png"
    },
    {
      "index": 5,
      "name": "sluchajay",
      "width": 28,
      "height": 30,
      "url": "assets/cursors/G_REC_005.png",
      "path": "extracted_assets\\grp\\G_REC\\cursor_05_sluchajay.pgm",
      "previewPath": "web_port\\assets\\cursors\\G_REC_005.png"
    }
  ],
  "components": [
    {
      "id": "00_Sprite_Holder",
      "type": "Sprite_Holder",
      "sourceType": "Group.Sprite_Holder",
      "namespace": "Group",
      "index": 0,
      "z": 0,
      "visible": true,
      "rect": {
        "x": 70,
        "y": 0,
        "width": 730,
        "height": 480
      },
      "geometryConfidence": "serialized_entries",
      "itemCount": 37,
      "hitboxes": [],
      "sourceOffset": 5340,
      "geometrySourceOffset": null,
      "privateOffset": 6880,
      "privateSize": 147768,
      "primaryAssetUrl": "../extracted_assets/grp/G_REC/sprite_holder/00_Group.Sprite_Holder_000_nagrywani_phase_00.png",
      "assets": [
        {
          "kind": "sprite_holder_png",
          "path": "extracted_assets\\grp\\G_REC\\sprite_holder\\00_Group.Sprite_Holder_000_nagrywani_phase_00.png",
          "url": "../extracted_assets/grp/G_REC/sprite_holder/00_Group.Sprite_Holder_000_nagrywani_phase_00.png",
          "renderPath": "extracted_assets\\grp\\G_REC\\sprite_holder\\00_Group.Sprite_Holder_000_nagrywani_phase_00.png",
          "stillPath": null,
          "stillUrl": null,
          "width": 35,
          "height": 42,
          "frameCount": null,
          "offset": 7080,
          "name": "nagrywani",
          "id": 0,
          "definitionId": 0,
          "phaseAssets": [
            {
              "phase": 0,
              "path": "extracted_assets\\grp\\G_REC\\sprite_holder\\00_Group.Sprite_Holder_000_nagrywani_phase_00.png",
              "url": "../extracted_assets/grp/G_REC/sprite_holder/00_Group.Sprite_Holder_000_nagrywani_phase_00.png"
            },
            {
              "phase": 1,
              "path": "extracted_assets\\grp\\G_REC\\sprite_holder\\00_Group.Sprite_Holder_000_nagrywani_phase_01.png",
              "url": "../extracted_assets/grp/G_REC/sprite_holder/00_Group.Sprite_Holder_000_nagrywani_phase_01.png"
            },
            {
              "phase": 2,
              "path": "extracted_assets\\grp\\G_REC\\sprite_holder\\00_Group.Sprite_Holder_000_nagrywani_phase_02.png",
              "url": "../extracted_assets/grp/G_REC/sprite_holder/00_Group.Sprite_Holder_000_nagrywani_phase_02.png"
            }
          ],
          "phaseCount": 3,
          "instanceOffset": 149468,
          "rect": {
            "x": 70,
            "y": 422,
            "width": 35,
            "height": 42
          },
          "geometryConfidence": "serialized_instance",
          "initialPhase": 2,
          "initiallyVisible": true,
          "draggable": false,
          "z": 0
        },
        {
          "kind": "sprite_holder_png",
          "path": "extracted_assets\\grp\\G_REC\\sprite_holder\\00_Group.Sprite_Holder_001_stop 01_phase_00.png",
          "url": "../extracted_assets/grp/G_REC/sprite_holder/00_Group.Sprite_Holder_001_stop 01_phase_00.png",
          "renderPath": "extracted_assets\\grp\\G_REC\\sprite_holder\\00_Group.Sprite_Holder_001_stop 01_phase_00.png",
          "stillPath": null,
          "stillUrl": null,
          "width": 37,
          "height": 38,
          "frameCount": null,
          "offset": 13548,
          "name": "stop 01",
          "id": 1,
          "definitionId": 1,
          "phaseAssets": [
            {
              "phase": 0,
              "path": "extracted_assets\\grp\\G_REC\\sprite_holder\\00_Group.Sprite_Holder_001_stop 01_phase_00.png",
              "url": "../extracted_assets/grp/G_REC/sprite_holder/00_Group.Sprite_Holder_001_stop 01_phase_00.png"
            },
            {
              "phase": 1,
              "path": "extracted_assets\\grp\\G_REC\\sprite_holder\\00_Group.Sprite_Holder_001_stop 01_phase_01.png",
              "url": "../extracted_assets/grp/G_REC/sprite_holder/00_Group.Sprite_Holder_001_stop 01_phase_01.png"
            },
            {
              "phase": 2,
              "path": "extracted_assets\\grp\\G_REC\\sprite_holder\\00_Group.Sprite_Holder_001_stop 01_phase_02.png",
              "url": "../extracted_assets/grp/G_REC/sprite_holder/00_Group.Sprite_Holder_001_stop 01_phase_02.png"
            }
          ],
          "phaseCount": 3,
          "instanceOffset": 149608,
          "rect": {
            "x": 166,
            "y": 424,
            "width": 37,
            "height": 38
          },
          "geometryConfidence": "serialized_instance",
          "initialPhase": 2,
          "initiallyVisible": true,
          "draggable": false,
          "z": 0
        },
        {
          "kind": "sprite_holder_png",
          "path": "extracted_assets\\grp\\G_REC\\sprite_holder\\00_Group.Sprite_Holder_002_play 01_phase_00.png",
          "url": "../extracted_assets/grp/G_REC/sprite_holder/00_Group.Sprite_Holder_002_play 01_phase_00.png",
          "renderPath": "extracted_assets\\grp\\G_REC\\sprite_holder\\00_Group.Sprite_Holder_002_play 01_phase_00.png",
          "stillPath": null,
          "stillUrl": null,
          "width": 34,
          "height": 42,
          "frameCount": null,
          "offset": 18528,
          "name": "play 01",
          "id": 2,
          "definitionId": 2,
          "phaseAssets": [
            {
              "phase": 0,
              "path": "extracted_assets\\grp\\G_REC\\sprite_holder\\00_Group.Sprite_Holder_002_play 01_phase_00.png",
              "url": "../extracted_assets/grp/G_REC/sprite_holder/00_Group.Sprite_Holder_002_play 01_phase_00.png"
            },
            {
              "phase": 1,
              "path": "extracted_assets\\grp\\G_REC\\sprite_holder\\00_Group.Sprite_Holder_002_play 01_phase_01.png",
              "url": "../extracted_assets/grp/G_REC/sprite_holder/00_Group.Sprite_Holder_002_play 01_phase_01.png"
            },
            {
              "phase": 2,
              "path": "extracted_assets\\grp\\G_REC\\sprite_holder\\00_Group.Sprite_Holder_002_play 01_phase_02.png",
              "url": "../extracted_assets/grp/G_REC/sprite_holder/00_Group.Sprite_Holder_002_play 01_phase_02.png"
            }
          ],
          "phaseCount": 3,
          "instanceOffset": 149748,
          "rect": {
            "x": 120,
            "y": 422,
            "width": 34,
            "height": 42
          },
          "geometryConfidence": "serialized_instance",
          "initialPhase": 2,
          "initiallyVisible": true,
          "draggable": false,
          "z": 0
        },
        {
          "kind": "sprite_holder_png",
          "path": "extracted_assets\\grp\\G_REC\\sprite_holder\\00_Group.Sprite_Holder_003_czas 02a_phase_00.png",
          "url": "../extracted_assets/grp/G_REC/sprite_holder/00_Group.Sprite_Holder_003_czas 02a_phase_00.png",
          "renderPath": "extracted_assets\\grp\\G_REC\\sprite_holder\\00_Group.Sprite_Holder_003_czas 02a_phase_00.png",
          "stillPath": null,
          "stillUrl": null,
          "width": 64,
          "height": 9,
          "frameCount": null,
          "offset": 24828,
          "name": "czas 02a",
          "id": 3,
          "definitionId": 3,
          "phaseAssets": [
            {
              "phase": 0,
              "path": "extracted_assets\\grp\\G_REC\\sprite_holder\\00_Group.Sprite_Holder_003_czas 02a_phase_00.png",
              "url": "../extracted_assets/grp/G_REC/sprite_holder/00_Group.Sprite_Holder_003_czas 02a_phase_00.png"
            }
          ],
          "phaseCount": 1,
          "instanceOffset": 149888,
          "rect": {
            "x": 547,
            "y": 433,
            "width": 64,
            "height": 9
          },
          "geometryConfidence": "serialized_instance",
          "initialPhase": 0,
          "initiallyVisible": true,
          "draggable": false,
          "z": 1
        },
        {
          "kind": "sprite_holder_png",
          "path": "extracted_assets\\grp\\G_REC\\sprite_holder\\00_Group.Sprite_Holder_004_ca_o_ 01_phase_00.png",
          "url": "../extracted_assets/grp/G_REC/sprite_holder/00_Group.Sprite_Holder_004_ca_o_ 01_phase_00.png",
          "renderPath": "extracted_assets\\grp\\G_REC\\sprite_holder\\00_Group.Sprite_Holder_004_ca_o_ 01_phase_00.png",
          "stillPath": null,
          "stillUrl": null,
          "width": 68,
          "height": 40,
          "frameCount": null,
          "offset": 25684,
          "name": "całość 01",
          "id": 4,
          "definitionId": 4,
          "phaseAssets": [
            {
              "phase": 0,
              "path": "extracted_assets\\grp\\G_REC\\sprite_holder\\00_Group.Sprite_Holder_004_ca_o_ 01_phase_00.png",
              "url": "../extracted_assets/grp/G_REC/sprite_holder/00_Group.Sprite_Holder_004_ca_o_ 01_phase_00.png"
            },
            {
              "phase": 1,
              "path": "extracted_assets\\grp\\G_REC\\sprite_holder\\00_Group.Sprite_Holder_004_ca_o_ 01_phase_01.png",
              "url": "../extracted_assets/grp/G_REC/sprite_holder/00_Group.Sprite_Holder_004_ca_o_ 01_phase_01.png"
            },
            {
              "phase": 2,
              "path": "extracted_assets\\grp\\G_REC\\sprite_holder\\00_Group.Sprite_Holder_004_ca_o_ 01_phase_02.png",
              "url": "../extracted_assets/grp/G_REC/sprite_holder/00_Group.Sprite_Holder_004_ca_o_ 01_phase_02.png"
            }
          ],
          "phaseCount": 3,
          "instanceOffset": 150028,
          "rect": {
            "x": 221,
            "y": 423,
            "width": 68,
            "height": 40
          },
          "geometryConfidence": "serialized_instance",
          "initialPhase": 2,
          "initiallyVisible": true,
          "draggable": false,
          "z": 0
        },
        {
          "kind": "sprite_holder_png",
          "path": "extracted_assets\\grp\\G_REC\\sprite_holder\\00_Group.Sprite_Holder_005_kasowanie_phase_00.png",
          "url": "../extracted_assets/grp/G_REC/sprite_holder/00_Group.Sprite_Holder_005_kasowanie_phase_00.png",
          "renderPath": "extracted_assets\\grp\\G_REC\\sprite_holder\\00_Group.Sprite_Holder_005_kasowanie_phase_00.png",
          "stillPath": null,
          "stillUrl": null,
          "width": 36,
          "height": 43,
          "frameCount": null,
          "offset": 36984,
          "name": "kasowanie",
          "id": 5,
          "definitionId": 5,
          "phaseAssets": [
            {
              "phase": 0,
              "path": "extracted_assets\\grp\\G_REC\\sprite_holder\\00_Group.Sprite_Holder_005_kasowanie_phase_00.png",
              "url": "../extracted_assets/grp/G_REC/sprite_holder/00_Group.Sprite_Holder_005_kasowanie_phase_00.png"
            },
            {
              "phase": 1,
              "path": "extracted_assets\\grp\\G_REC\\sprite_holder\\00_Group.Sprite_Holder_005_kasowanie_phase_01.png",
              "url": "../extracted_assets/grp/G_REC/sprite_holder/00_Group.Sprite_Holder_005_kasowanie_phase_01.png"
            },
            {
              "phase": 2,
              "path": "extracted_assets\\grp\\G_REC\\sprite_holder\\00_Group.Sprite_Holder_005_kasowanie_phase_02.png",
              "url": "../extracted_assets/grp/G_REC/sprite_holder/00_Group.Sprite_Holder_005_kasowanie_phase_02.png"
            }
          ],
          "phaseCount": 3,
          "instanceOffset": 150168,
          "rect": {
            "x": 302,
            "y": 421,
            "width": 36,
            "height": 43
          },
          "geometryConfidence": "serialized_instance",
          "initialPhase": 2,
          "initiallyVisible": true,
          "draggable": false,
          "z": 0
        },
        {
          "kind": "sprite_holder_png",
          "path": "extracted_assets\\grp\\G_REC\\sprite_holder\\00_Group.Sprite_Holder_006_ilo_ 01_phase_00.png",
          "url": "../extracted_assets/grp/G_REC/sprite_holder/00_Group.Sprite_Holder_006_ilo_ 01_phase_00.png",
          "renderPath": "extracted_assets\\grp\\G_REC\\sprite_holder\\00_Group.Sprite_Holder_006_ilo_ 01_phase_00.png",
          "stillPath": null,
          "stillUrl": null,
          "width": 18,
          "height": 19,
          "frameCount": null,
          "offset": 42048,
          "name": "ilość 01",
          "id": 6,
          "definitionId": 6,
          "phaseAssets": [
            {
              "phase": 0,
              "path": "extracted_assets\\grp\\G_REC\\sprite_holder\\00_Group.Sprite_Holder_006_ilo_ 01_phase_00.png",
              "url": "../extracted_assets/grp/G_REC/sprite_holder/00_Group.Sprite_Holder_006_ilo_ 01_phase_00.png"
            },
            {
              "phase": 1,
              "path": "extracted_assets\\grp\\G_REC\\sprite_holder\\00_Group.Sprite_Holder_006_ilo_ 01_phase_01.png",
              "url": "../extracted_assets/grp/G_REC/sprite_holder/00_Group.Sprite_Holder_006_ilo_ 01_phase_01.png"
            },
            {
              "phase": 2,
              "path": "extracted_assets\\grp\\G_REC\\sprite_holder\\00_Group.Sprite_Holder_006_ilo_ 01_phase_02.png",
              "url": "../extracted_assets/grp/G_REC/sprite_holder/00_Group.Sprite_Holder_006_ilo_ 01_phase_02.png"
            },
            {
              "phase": 3,
              "path": "extracted_assets\\grp\\G_REC\\sprite_holder\\00_Group.Sprite_Holder_006_ilo_ 01_phase_03.png",
              "url": "../extracted_assets/grp/G_REC/sprite_holder/00_Group.Sprite_Holder_006_ilo_ 01_phase_03.png"
            },
            {
              "phase": 4,
              "path": "extracted_assets\\grp\\G_REC\\sprite_holder\\00_Group.Sprite_Holder_006_ilo_ 01_phase_04.png",
              "url": "../extracted_assets/grp/G_REC/sprite_holder/00_Group.Sprite_Holder_006_ilo_ 01_phase_04.png"
            }
          ],
          "phaseCount": 5,
          "instanceOffset": 150308,
          "rect": {
            "x": 354,
            "y": 424,
            "width": 18,
            "height": 19
          },
          "geometryConfidence": "serialized_instance",
          "initialPhase": 0,
          "initiallyVisible": true,
          "draggable": false,
          "z": 0
        },
        {
          "kind": "sprite_holder_png",
          "path": "extracted_assets\\grp\\G_REC\\sprite_holder\\00_Group.Sprite_Holder_006_ilo_ 01_phase_00.png",
          "url": "../extracted_assets/grp/G_REC/sprite_holder/00_Group.Sprite_Holder_006_ilo_ 01_phase_00.png",
          "renderPath": "extracted_assets\\grp\\G_REC\\sprite_holder\\00_Group.Sprite_Holder_006_ilo_ 01_phase_00.png",
          "stillPath": null,
          "stillUrl": null,
          "width": 18,
          "height": 19,
          "frameCount": null,
          "offset": 42048,
          "name": "ilość 01",
          "id": 7,
          "definitionId": 6,
          "phaseAssets": [
            {
              "phase": 0,
              "path": "extracted_assets\\grp\\G_REC\\sprite_holder\\00_Group.Sprite_Holder_006_ilo_ 01_phase_00.png",
              "url": "../extracted_assets/grp/G_REC/sprite_holder/00_Group.Sprite_Holder_006_ilo_ 01_phase_00.png"
            },
            {
              "phase": 1,
              "path": "extracted_assets\\grp\\G_REC\\sprite_holder\\00_Group.Sprite_Holder_006_ilo_ 01_phase_01.png",
              "url": "../extracted_assets/grp/G_REC/sprite_holder/00_Group.Sprite_Holder_006_ilo_ 01_phase_01.png"
            },
            {
              "phase": 2,
              "path": "extracted_assets\\grp\\G_REC\\sprite_holder\\00_Group.Sprite_Holder_006_ilo_ 01_phase_02.png",
              "url": "../extracted_assets/grp/G_REC/sprite_holder/00_Group.Sprite_Holder_006_ilo_ 01_phase_02.png"
            },
            {
              "phase": 3,
              "path": "extracted_assets\\grp\\G_REC\\sprite_holder\\00_Group.Sprite_Holder_006_ilo_ 01_phase_03.png",
              "url": "../extracted_assets/grp/G_REC/sprite_holder/00_Group.Sprite_Holder_006_ilo_ 01_phase_03.png"
            },
            {
              "phase": 4,
              "path": "extracted_assets\\grp\\G_REC\\sprite_holder\\00_Group.Sprite_Holder_006_ilo_ 01_phase_04.png",
              "url": "../extracted_assets/grp/G_REC/sprite_holder/00_Group.Sprite_Holder_006_ilo_ 01_phase_04.png"
            }
          ],
          "phaseCount": 5,
          "instanceOffset": 150448,
          "rect": {
            "x": 373,
            "y": 424,
            "width": 18,
            "height": 19
          },
          "geometryConfidence": "serialized_instance",
          "initialPhase": 0,
          "initiallyVisible": true,
          "draggable": false,
          "z": 0
        },
        {
          "kind": "sprite_holder_png",
          "path": "extracted_assets\\grp\\G_REC\\sprite_holder\\00_Group.Sprite_Holder_006_ilo_ 01_phase_00.png",
          "url": "../extracted_assets/grp/G_REC/sprite_holder/00_Group.Sprite_Holder_006_ilo_ 01_phase_00.png",
          "renderPath": "extracted_assets\\grp\\G_REC\\sprite_holder\\00_Group.Sprite_Holder_006_ilo_ 01_phase_00.png",
          "stillPath": null,
          "stillUrl": null,
          "width": 18,
          "height": 19,
          "frameCount": null,
          "offset": 42048,
          "name": "ilość 01",
          "id": 8,
          "definitionId": 6,
          "phaseAssets": [
            {
              "phase": 0,
              "path": "extracted_assets\\grp\\G_REC\\sprite_holder\\00_Group.Sprite_Holder_006_ilo_ 01_phase_00.png",
              "url": "../extracted_assets/grp/G_REC/sprite_holder/00_Group.Sprite_Holder_006_ilo_ 01_phase_00.png"
            },
            {
              "phase": 1,
              "path": "extracted_assets\\grp\\G_REC\\sprite_holder\\00_Group.Sprite_Holder_006_ilo_ 01_phase_01.png",
              "url": "../extracted_assets/grp/G_REC/sprite_holder/00_Group.Sprite_Holder_006_ilo_ 01_phase_01.png"
            },
            {
              "phase": 2,
              "path": "extracted_assets\\grp\\G_REC\\sprite_holder\\00_Group.Sprite_Holder_006_ilo_ 01_phase_02.png",
              "url": "../extracted_assets/grp/G_REC/sprite_holder/00_Group.Sprite_Holder_006_ilo_ 01_phase_02.png"
            },
            {
              "phase": 3,
              "path": "extracted_assets\\grp\\G_REC\\sprite_holder\\00_Group.Sprite_Holder_006_ilo_ 01_phase_03.png",
              "url": "../extracted_assets/grp/G_REC/sprite_holder/00_Group.Sprite_Holder_006_ilo_ 01_phase_03.png"
            },
            {
              "phase": 4,
              "path": "extracted_assets\\grp\\G_REC\\sprite_holder\\00_Group.Sprite_Holder_006_ilo_ 01_phase_04.png",
              "url": "../extracted_assets/grp/G_REC/sprite_holder/00_Group.Sprite_Holder_006_ilo_ 01_phase_04.png"
            }
          ],
          "phaseCount": 5,
          "instanceOffset": 150588,
          "rect": {
            "x": 392,
            "y": 424,
            "width": 18,
            "height": 19
          },
          "geometryConfidence": "serialized_instance",
          "initialPhase": 0,
          "initiallyVisible": true,
          "draggable": false,
          "z": 0
        },
        {
          "kind": "sprite_holder_png",
          "path": "extracted_assets\\grp\\G_REC\\sprite_holder\\00_Group.Sprite_Holder_006_ilo_ 01_phase_00.png",
          "url": "../extracted_assets/grp/G_REC/sprite_holder/00_Group.Sprite_Holder_006_ilo_ 01_phase_00.png",
          "renderPath": "extracted_assets\\grp\\G_REC\\sprite_holder\\00_Group.Sprite_Holder_006_ilo_ 01_phase_00.png",
          "stillPath": null,
          "stillUrl": null,
          "width": 18,
          "height": 19,
          "frameCount": null,
          "offset": 42048,
          "name": "ilość 01",
          "id": 9,
          "definitionId": 6,
          "phaseAssets": [
            {
              "phase": 0,
              "path": "extracted_assets\\grp\\G_REC\\sprite_holder\\00_Group.Sprite_Holder_006_ilo_ 01_phase_00.png",
              "url": "../extracted_assets/grp/G_REC/sprite_holder/00_Group.Sprite_Holder_006_ilo_ 01_phase_00.png"
            },
            {
              "phase": 1,
              "path": "extracted_assets\\grp\\G_REC\\sprite_holder\\00_Group.Sprite_Holder_006_ilo_ 01_phase_01.png",
              "url": "../extracted_assets/grp/G_REC/sprite_holder/00_Group.Sprite_Holder_006_ilo_ 01_phase_01.png"
            },
            {
              "phase": 2,
              "path": "extracted_assets\\grp\\G_REC\\sprite_holder\\00_Group.Sprite_Holder_006_ilo_ 01_phase_02.png",
              "url": "../extracted_assets/grp/G_REC/sprite_holder/00_Group.Sprite_Holder_006_ilo_ 01_phase_02.png"
            },
            {
              "phase": 3,
              "path": "extracted_assets\\grp\\G_REC\\sprite_holder\\00_Group.Sprite_Holder_006_ilo_ 01_phase_03.png",
              "url": "../extracted_assets/grp/G_REC/sprite_holder/00_Group.Sprite_Holder_006_ilo_ 01_phase_03.png"
            },
            {
              "phase": 4,
              "path": "extracted_assets\\grp\\G_REC\\sprite_holder\\00_Group.Sprite_Holder_006_ilo_ 01_phase_04.png",
              "url": "../extracted_assets/grp/G_REC/sprite_holder/00_Group.Sprite_Holder_006_ilo_ 01_phase_04.png"
            }
          ],
          "phaseCount": 5,
          "instanceOffset": 150728,
          "rect": {
            "x": 411,
            "y": 424,
            "width": 18,
            "height": 19
          },
          "geometryConfidence": "serialized_instance",
          "initialPhase": 0,
          "initiallyVisible": true,
          "draggable": false,
          "z": 0
        },
        {
          "kind": "sprite_holder_png",
          "path": "extracted_assets\\grp\\G_REC\\sprite_holder\\00_Group.Sprite_Holder_006_ilo_ 01_phase_00.png",
          "url": "../extracted_assets/grp/G_REC/sprite_holder/00_Group.Sprite_Holder_006_ilo_ 01_phase_00.png",
          "renderPath": "extracted_assets\\grp\\G_REC\\sprite_holder\\00_Group.Sprite_Holder_006_ilo_ 01_phase_00.png",
          "stillPath": null,
          "stillUrl": null,
          "width": 18,
          "height": 19,
          "frameCount": null,
          "offset": 42048,
          "name": "ilość 01",
          "id": 10,
          "definitionId": 6,
          "phaseAssets": [
            {
              "phase": 0,
              "path": "extracted_assets\\grp\\G_REC\\sprite_holder\\00_Group.Sprite_Holder_006_ilo_ 01_phase_00.png",
              "url": "../extracted_assets/grp/G_REC/sprite_holder/00_Group.Sprite_Holder_006_ilo_ 01_phase_00.png"
            },
            {
              "phase": 1,
              "path": "extracted_assets\\grp\\G_REC\\sprite_holder\\00_Group.Sprite_Holder_006_ilo_ 01_phase_01.png",
              "url": "../extracted_assets/grp/G_REC/sprite_holder/00_Group.Sprite_Holder_006_ilo_ 01_phase_01.png"
            },
            {
              "phase": 2,
              "path": "extracted_assets\\grp\\G_REC\\sprite_holder\\00_Group.Sprite_Holder_006_ilo_ 01_phase_02.png",
              "url": "../extracted_assets/grp/G_REC/sprite_holder/00_Group.Sprite_Holder_006_ilo_ 01_phase_02.png"
            },
            {
              "phase": 3,
              "path": "extracted_assets\\grp\\G_REC\\sprite_holder\\00_Group.Sprite_Holder_006_ilo_ 01_phase_03.png",
              "url": "../extracted_assets/grp/G_REC/sprite_holder/00_Group.Sprite_Holder_006_ilo_ 01_phase_03.png"
            },
            {
              "phase": 4,
              "path": "extracted_assets\\grp\\G_REC\\sprite_holder\\00_Group.Sprite_Holder_006_ilo_ 01_phase_04.png",
              "url": "../extracted_assets/grp/G_REC/sprite_holder/00_Group.Sprite_Holder_006_ilo_ 01_phase_04.png"
            }
          ],
          "phaseCount": 5,
          "instanceOffset": 150868,
          "rect": {
            "x": 429,
            "y": 424,
            "width": 18,
            "height": 19
          },
          "geometryConfidence": "serialized_instance",
          "initialPhase": 0,
          "initiallyVisible": true,
          "draggable": false,
          "z": 0
        },
        {
          "kind": "sprite_holder_png",
          "path": "extracted_assets\\grp\\G_REC\\sprite_holder\\00_Group.Sprite_Holder_006_ilo_ 01_phase_00.png",
          "url": "../extracted_assets/grp/G_REC/sprite_holder/00_Group.Sprite_Holder_006_ilo_ 01_phase_00.png",
          "renderPath": "extracted_assets\\grp\\G_REC\\sprite_holder\\00_Group.Sprite_Holder_006_ilo_ 01_phase_00.png",
          "stillPath": null,
          "stillUrl": null,
          "width": 18,
          "height": 19,
          "frameCount": null,
          "offset": 42048,
          "name": "ilość 01",
          "id": 11,
          "definitionId": 6,
          "phaseAssets": [
            {
              "phase": 0,
              "path": "extracted_assets\\grp\\G_REC\\sprite_holder\\00_Group.Sprite_Holder_006_ilo_ 01_phase_00.png",
              "url": "../extracted_assets/grp/G_REC/sprite_holder/00_Group.Sprite_Holder_006_ilo_ 01_phase_00.png"
            },
            {
              "phase": 1,
              "path": "extracted_assets\\grp\\G_REC\\sprite_holder\\00_Group.Sprite_Holder_006_ilo_ 01_phase_01.png",
              "url": "../extracted_assets/grp/G_REC/sprite_holder/00_Group.Sprite_Holder_006_ilo_ 01_phase_01.png"
            },
            {
              "phase": 2,
              "path": "extracted_assets\\grp\\G_REC\\sprite_holder\\00_Group.Sprite_Holder_006_ilo_ 01_phase_02.png",
              "url": "../extracted_assets/grp/G_REC/sprite_holder/00_Group.Sprite_Holder_006_ilo_ 01_phase_02.png"
            },
            {
              "phase": 3,
              "path": "extracted_assets\\grp\\G_REC\\sprite_holder\\00_Group.Sprite_Holder_006_ilo_ 01_phase_03.png",
              "url": "../extracted_assets/grp/G_REC/sprite_holder/00_Group.Sprite_Holder_006_ilo_ 01_phase_03.png"
            },
            {
              "phase": 4,
              "path": "extracted_assets\\grp\\G_REC\\sprite_holder\\00_Group.Sprite_Holder_006_ilo_ 01_phase_04.png",
              "url": "../extracted_assets/grp/G_REC/sprite_holder/00_Group.Sprite_Holder_006_ilo_ 01_phase_04.png"
            }
          ],
          "phaseCount": 5,
          "instanceOffset": 151008,
          "rect": {
            "x": 448,
            "y": 424,
            "width": 18,
            "height": 19
          },
          "geometryConfidence": "serialized_instance",
          "initialPhase": 0,
          "initiallyVisible": true,
          "draggable": false,
          "z": 0
        },
        {
          "kind": "sprite_holder_png",
          "path": "extracted_assets\\grp\\G_REC\\sprite_holder\\00_Group.Sprite_Holder_006_ilo_ 01_phase_00.png",
          "url": "../extracted_assets/grp/G_REC/sprite_holder/00_Group.Sprite_Holder_006_ilo_ 01_phase_00.png",
          "renderPath": "extracted_assets\\grp\\G_REC\\sprite_holder\\00_Group.Sprite_Holder_006_ilo_ 01_phase_00.png",
          "stillPath": null,
          "stillUrl": null,
          "width": 18,
          "height": 19,
          "frameCount": null,
          "offset": 42048,
          "name": "ilość 01",
          "id": 12,
          "definitionId": 6,
          "phaseAssets": [
            {
              "phase": 0,
              "path": "extracted_assets\\grp\\G_REC\\sprite_holder\\00_Group.Sprite_Holder_006_ilo_ 01_phase_00.png",
              "url": "../extracted_assets/grp/G_REC/sprite_holder/00_Group.Sprite_Holder_006_ilo_ 01_phase_00.png"
            },
            {
              "phase": 1,
              "path": "extracted_assets\\grp\\G_REC\\sprite_holder\\00_Group.Sprite_Holder_006_ilo_ 01_phase_01.png",
              "url": "../extracted_assets/grp/G_REC/sprite_holder/00_Group.Sprite_Holder_006_ilo_ 01_phase_01.png"
            },
            {
              "phase": 2,
              "path": "extracted_assets\\grp\\G_REC\\sprite_holder\\00_Group.Sprite_Holder_006_ilo_ 01_phase_02.png",
              "url": "../extracted_assets/grp/G_REC/sprite_holder/00_Group.Sprite_Holder_006_ilo_ 01_phase_02.png"
            },
            {
              "phase": 3,
              "path": "extracted_assets\\grp\\G_REC\\sprite_holder\\00_Group.Sprite_Holder_006_ilo_ 01_phase_03.png",
              "url": "../extracted_assets/grp/G_REC/sprite_holder/00_Group.Sprite_Holder_006_ilo_ 01_phase_03.png"
            },
            {
              "phase": 4,
              "path": "extracted_assets\\grp\\G_REC\\sprite_holder\\00_Group.Sprite_Holder_006_ilo_ 01_phase_04.png",
              "url": "../extracted_assets/grp/G_REC/sprite_holder/00_Group.Sprite_Holder_006_ilo_ 01_phase_04.png"
            }
          ],
          "phaseCount": 5,
          "instanceOffset": 151148,
          "rect": {
            "x": 466,
            "y": 424,
            "width": 18,
            "height": 19
          },
          "geometryConfidence": "serialized_instance",
          "initialPhase": 0,
          "initiallyVisible": true,
          "draggable": false,
          "z": 0
        },
        {
          "kind": "sprite_holder_png",
          "path": "extracted_assets\\grp\\G_REC\\sprite_holder\\00_Group.Sprite_Holder_006_ilo_ 01_phase_00.png",
          "url": "../extracted_assets/grp/G_REC/sprite_holder/00_Group.Sprite_Holder_006_ilo_ 01_phase_00.png",
          "renderPath": "extracted_assets\\grp\\G_REC\\sprite_holder\\00_Group.Sprite_Holder_006_ilo_ 01_phase_00.png",
          "stillPath": null,
          "stillUrl": null,
          "width": 18,
          "height": 19,
          "frameCount": null,
          "offset": 42048,
          "name": "ilość 01",
          "id": 13,
          "definitionId": 6,
          "phaseAssets": [
            {
              "phase": 0,
              "path": "extracted_assets\\grp\\G_REC\\sprite_holder\\00_Group.Sprite_Holder_006_ilo_ 01_phase_00.png",
              "url": "../extracted_assets/grp/G_REC/sprite_holder/00_Group.Sprite_Holder_006_ilo_ 01_phase_00.png"
            },
            {
              "phase": 1,
              "path": "extracted_assets\\grp\\G_REC\\sprite_holder\\00_Group.Sprite_Holder_006_ilo_ 01_phase_01.png",
              "url": "../extracted_assets/grp/G_REC/sprite_holder/00_Group.Sprite_Holder_006_ilo_ 01_phase_01.png"
            },
            {
              "phase": 2,
              "path": "extracted_assets\\grp\\G_REC\\sprite_holder\\00_Group.Sprite_Holder_006_ilo_ 01_phase_02.png",
              "url": "../extracted_assets/grp/G_REC/sprite_holder/00_Group.Sprite_Holder_006_ilo_ 01_phase_02.png"
            },
            {
              "phase": 3,
              "path": "extracted_assets\\grp\\G_REC\\sprite_holder\\00_Group.Sprite_Holder_006_ilo_ 01_phase_03.png",
              "url": "../extracted_assets/grp/G_REC/sprite_holder/00_Group.Sprite_Holder_006_ilo_ 01_phase_03.png"
            },
            {
              "phase": 4,
              "path": "extracted_assets\\grp\\G_REC\\sprite_holder\\00_Group.Sprite_Holder_006_ilo_ 01_phase_04.png",
              "url": "../extracted_assets/grp/G_REC/sprite_holder/00_Group.Sprite_Holder_006_ilo_ 01_phase_04.png"
            }
          ],
          "phaseCount": 5,
          "instanceOffset": 151288,
          "rect": {
            "x": 365,
            "y": 442,
            "width": 18,
            "height": 19
          },
          "geometryConfidence": "serialized_instance",
          "initialPhase": 0,
          "initiallyVisible": true,
          "draggable": false,
          "z": 0
        },
        {
          "kind": "sprite_holder_png",
          "path": "extracted_assets\\grp\\G_REC\\sprite_holder\\00_Group.Sprite_Holder_006_ilo_ 01_phase_00.png",
          "url": "../extracted_assets/grp/G_REC/sprite_holder/00_Group.Sprite_Holder_006_ilo_ 01_phase_00.png",
          "renderPath": "extracted_assets\\grp\\G_REC\\sprite_holder\\00_Group.Sprite_Holder_006_ilo_ 01_phase_00.png",
          "stillPath": null,
          "stillUrl": null,
          "width": 18,
          "height": 19,
          "frameCount": null,
          "offset": 42048,
          "name": "ilość 01",
          "id": 14,
          "definitionId": 6,
          "phaseAssets": [
            {
              "phase": 0,
              "path": "extracted_assets\\grp\\G_REC\\sprite_holder\\00_Group.Sprite_Holder_006_ilo_ 01_phase_00.png",
              "url": "../extracted_assets/grp/G_REC/sprite_holder/00_Group.Sprite_Holder_006_ilo_ 01_phase_00.png"
            },
            {
              "phase": 1,
              "path": "extracted_assets\\grp\\G_REC\\sprite_holder\\00_Group.Sprite_Holder_006_ilo_ 01_phase_01.png",
              "url": "../extracted_assets/grp/G_REC/sprite_holder/00_Group.Sprite_Holder_006_ilo_ 01_phase_01.png"
            },
            {
              "phase": 2,
              "path": "extracted_assets\\grp\\G_REC\\sprite_holder\\00_Group.Sprite_Holder_006_ilo_ 01_phase_02.png",
              "url": "../extracted_assets/grp/G_REC/sprite_holder/00_Group.Sprite_Holder_006_ilo_ 01_phase_02.png"
            },
            {
              "phase": 3,
              "path": "extracted_assets\\grp\\G_REC\\sprite_holder\\00_Group.Sprite_Holder_006_ilo_ 01_phase_03.png",
              "url": "../extracted_assets/grp/G_REC/sprite_holder/00_Group.Sprite_Holder_006_ilo_ 01_phase_03.png"
            },
            {
              "phase": 4,
              "path": "extracted_assets\\grp\\G_REC\\sprite_holder\\00_Group.Sprite_Holder_006_ilo_ 01_phase_04.png",
              "url": "../extracted_assets/grp/G_REC/sprite_holder/00_Group.Sprite_Holder_006_ilo_ 01_phase_04.png"
            }
          ],
          "phaseCount": 5,
          "instanceOffset": 151428,
          "rect": {
            "x": 383,
            "y": 442,
            "width": 18,
            "height": 19
          },
          "geometryConfidence": "serialized_instance",
          "initialPhase": 0,
          "initiallyVisible": true,
          "draggable": false,
          "z": 0
        },
        {
          "kind": "sprite_holder_png",
          "path": "extracted_assets\\grp\\G_REC\\sprite_holder\\00_Group.Sprite_Holder_006_ilo_ 01_phase_00.png",
          "url": "../extracted_assets/grp/G_REC/sprite_holder/00_Group.Sprite_Holder_006_ilo_ 01_phase_00.png",
          "renderPath": "extracted_assets\\grp\\G_REC\\sprite_holder\\00_Group.Sprite_Holder_006_ilo_ 01_phase_00.png",
          "stillPath": null,
          "stillUrl": null,
          "width": 18,
          "height": 19,
          "frameCount": null,
          "offset": 42048,
          "name": "ilość 01",
          "id": 15,
          "definitionId": 6,
          "phaseAssets": [
            {
              "phase": 0,
              "path": "extracted_assets\\grp\\G_REC\\sprite_holder\\00_Group.Sprite_Holder_006_ilo_ 01_phase_00.png",
              "url": "../extracted_assets/grp/G_REC/sprite_holder/00_Group.Sprite_Holder_006_ilo_ 01_phase_00.png"
            },
            {
              "phase": 1,
              "path": "extracted_assets\\grp\\G_REC\\sprite_holder\\00_Group.Sprite_Holder_006_ilo_ 01_phase_01.png",
              "url": "../extracted_assets/grp/G_REC/sprite_holder/00_Group.Sprite_Holder_006_ilo_ 01_phase_01.png"
            },
            {
              "phase": 2,
              "path": "extracted_assets\\grp\\G_REC\\sprite_holder\\00_Group.Sprite_Holder_006_ilo_ 01_phase_02.png",
              "url": "../extracted_assets/grp/G_REC/sprite_holder/00_Group.Sprite_Holder_006_ilo_ 01_phase_02.png"
            },
            {
              "phase": 3,
              "path": "extracted_assets\\grp\\G_REC\\sprite_holder\\00_Group.Sprite_Holder_006_ilo_ 01_phase_03.png",
              "url": "../extracted_assets/grp/G_REC/sprite_holder/00_Group.Sprite_Holder_006_ilo_ 01_phase_03.png"
            },
            {
              "phase": 4,
              "path": "extracted_assets\\grp\\G_REC\\sprite_holder\\00_Group.Sprite_Holder_006_ilo_ 01_phase_04.png",
              "url": "../extracted_assets/grp/G_REC/sprite_holder/00_Group.Sprite_Holder_006_ilo_ 01_phase_04.png"
            }
          ],
          "phaseCount": 5,
          "instanceOffset": 151568,
          "rect": {
            "x": 402,
            "y": 442,
            "width": 18,
            "height": 19
          },
          "geometryConfidence": "serialized_instance",
          "initialPhase": 0,
          "initiallyVisible": true,
          "draggable": false,
          "z": 0
        },
        {
          "kind": "sprite_holder_png",
          "path": "extracted_assets\\grp\\G_REC\\sprite_holder\\00_Group.Sprite_Holder_006_ilo_ 01_phase_00.png",
          "url": "../extracted_assets/grp/G_REC/sprite_holder/00_Group.Sprite_Holder_006_ilo_ 01_phase_00.png",
          "renderPath": "extracted_assets\\grp\\G_REC\\sprite_holder\\00_Group.Sprite_Holder_006_ilo_ 01_phase_00.png",
          "stillPath": null,
          "stillUrl": null,
          "width": 18,
          "height": 19,
          "frameCount": null,
          "offset": 42048,
          "name": "ilość 01",
          "id": 16,
          "definitionId": 6,
          "phaseAssets": [
            {
              "phase": 0,
              "path": "extracted_assets\\grp\\G_REC\\sprite_holder\\00_Group.Sprite_Holder_006_ilo_ 01_phase_00.png",
              "url": "../extracted_assets/grp/G_REC/sprite_holder/00_Group.Sprite_Holder_006_ilo_ 01_phase_00.png"
            },
            {
              "phase": 1,
              "path": "extracted_assets\\grp\\G_REC\\sprite_holder\\00_Group.Sprite_Holder_006_ilo_ 01_phase_01.png",
              "url": "../extracted_assets/grp/G_REC/sprite_holder/00_Group.Sprite_Holder_006_ilo_ 01_phase_01.png"
            },
            {
              "phase": 2,
              "path": "extracted_assets\\grp\\G_REC\\sprite_holder\\00_Group.Sprite_Holder_006_ilo_ 01_phase_02.png",
              "url": "../extracted_assets/grp/G_REC/sprite_holder/00_Group.Sprite_Holder_006_ilo_ 01_phase_02.png"
            },
            {
              "phase": 3,
              "path": "extracted_assets\\grp\\G_REC\\sprite_holder\\00_Group.Sprite_Holder_006_ilo_ 01_phase_03.png",
              "url": "../extracted_assets/grp/G_REC/sprite_holder/00_Group.Sprite_Holder_006_ilo_ 01_phase_03.png"
            },
            {
              "phase": 4,
              "path": "extracted_assets\\grp\\G_REC\\sprite_holder\\00_Group.Sprite_Holder_006_ilo_ 01_phase_04.png",
              "url": "../extracted_assets/grp/G_REC/sprite_holder/00_Group.Sprite_Holder_006_ilo_ 01_phase_04.png"
            }
          ],
          "phaseCount": 5,
          "instanceOffset": 151708,
          "rect": {
            "x": 420,
            "y": 442,
            "width": 18,
            "height": 19
          },
          "geometryConfidence": "serialized_instance",
          "initialPhase": 0,
          "initiallyVisible": true,
          "draggable": false,
          "z": 0
        },
        {
          "kind": "sprite_holder_png",
          "path": "extracted_assets\\grp\\G_REC\\sprite_holder\\00_Group.Sprite_Holder_006_ilo_ 01_phase_00.png",
          "url": "../extracted_assets/grp/G_REC/sprite_holder/00_Group.Sprite_Holder_006_ilo_ 01_phase_00.png",
          "renderPath": "extracted_assets\\grp\\G_REC\\sprite_holder\\00_Group.Sprite_Holder_006_ilo_ 01_phase_00.png",
          "stillPath": null,
          "stillUrl": null,
          "width": 18,
          "height": 19,
          "frameCount": null,
          "offset": 42048,
          "name": "ilość 01",
          "id": 17,
          "definitionId": 6,
          "phaseAssets": [
            {
              "phase": 0,
              "path": "extracted_assets\\grp\\G_REC\\sprite_holder\\00_Group.Sprite_Holder_006_ilo_ 01_phase_00.png",
              "url": "../extracted_assets/grp/G_REC/sprite_holder/00_Group.Sprite_Holder_006_ilo_ 01_phase_00.png"
            },
            {
              "phase": 1,
              "path": "extracted_assets\\grp\\G_REC\\sprite_holder\\00_Group.Sprite_Holder_006_ilo_ 01_phase_01.png",
              "url": "../extracted_assets/grp/G_REC/sprite_holder/00_Group.Sprite_Holder_006_ilo_ 01_phase_01.png"
            },
            {
              "phase": 2,
              "path": "extracted_assets\\grp\\G_REC\\sprite_holder\\00_Group.Sprite_Holder_006_ilo_ 01_phase_02.png",
              "url": "../extracted_assets/grp/G_REC/sprite_holder/00_Group.Sprite_Holder_006_ilo_ 01_phase_02.png"
            },
            {
              "phase": 3,
              "path": "extracted_assets\\grp\\G_REC\\sprite_holder\\00_Group.Sprite_Holder_006_ilo_ 01_phase_03.png",
              "url": "../extracted_assets/grp/G_REC/sprite_holder/00_Group.Sprite_Holder_006_ilo_ 01_phase_03.png"
            },
            {
              "phase": 4,
              "path": "extracted_assets\\grp\\G_REC\\sprite_holder\\00_Group.Sprite_Holder_006_ilo_ 01_phase_04.png",
              "url": "../extracted_assets/grp/G_REC/sprite_holder/00_Group.Sprite_Holder_006_ilo_ 01_phase_04.png"
            }
          ],
          "phaseCount": 5,
          "instanceOffset": 151848,
          "rect": {
            "x": 439,
            "y": 442,
            "width": 18,
            "height": 19
          },
          "geometryConfidence": "serialized_instance",
          "initialPhase": 0,
          "initiallyVisible": true,
          "draggable": false,
          "z": 0
        },
        {
          "kind": "sprite_holder_png",
          "path": "extracted_assets\\grp\\G_REC\\sprite_holder\\00_Group.Sprite_Holder_006_ilo_ 01_phase_00.png",
          "url": "../extracted_assets/grp/G_REC/sprite_holder/00_Group.Sprite_Holder_006_ilo_ 01_phase_00.png",
          "renderPath": "extracted_assets\\grp\\G_REC\\sprite_holder\\00_Group.Sprite_Holder_006_ilo_ 01_phase_00.png",
          "stillPath": null,
          "stillUrl": null,
          "width": 18,
          "height": 19,
          "frameCount": null,
          "offset": 42048,
          "name": "ilość 01",
          "id": 18,
          "definitionId": 6,
          "phaseAssets": [
            {
              "phase": 0,
              "path": "extracted_assets\\grp\\G_REC\\sprite_holder\\00_Group.Sprite_Holder_006_ilo_ 01_phase_00.png",
              "url": "../extracted_assets/grp/G_REC/sprite_holder/00_Group.Sprite_Holder_006_ilo_ 01_phase_00.png"
            },
            {
              "phase": 1,
              "path": "extracted_assets\\grp\\G_REC\\sprite_holder\\00_Group.Sprite_Holder_006_ilo_ 01_phase_01.png",
              "url": "../extracted_assets/grp/G_REC/sprite_holder/00_Group.Sprite_Holder_006_ilo_ 01_phase_01.png"
            },
            {
              "phase": 2,
              "path": "extracted_assets\\grp\\G_REC\\sprite_holder\\00_Group.Sprite_Holder_006_ilo_ 01_phase_02.png",
              "url": "../extracted_assets/grp/G_REC/sprite_holder/00_Group.Sprite_Holder_006_ilo_ 01_phase_02.png"
            },
            {
              "phase": 3,
              "path": "extracted_assets\\grp\\G_REC\\sprite_holder\\00_Group.Sprite_Holder_006_ilo_ 01_phase_03.png",
              "url": "../extracted_assets/grp/G_REC/sprite_holder/00_Group.Sprite_Holder_006_ilo_ 01_phase_03.png"
            },
            {
              "phase": 4,
              "path": "extracted_assets\\grp\\G_REC\\sprite_holder\\00_Group.Sprite_Holder_006_ilo_ 01_phase_04.png",
              "url": "../extracted_assets/grp/G_REC/sprite_holder/00_Group.Sprite_Holder_006_ilo_ 01_phase_04.png"
            }
          ],
          "phaseCount": 5,
          "instanceOffset": 151988,
          "rect": {
            "x": 458,
            "y": 442,
            "width": 18,
            "height": 19
          },
          "geometryConfidence": "serialized_instance",
          "initialPhase": 0,
          "initiallyVisible": true,
          "draggable": false,
          "z": 0
        },
        {
          "kind": "sprite_holder_png",
          "path": "extracted_assets\\grp\\G_REC\\sprite_holder\\00_Group.Sprite_Holder_006_ilo_ 01_phase_00.png",
          "url": "../extracted_assets/grp/G_REC/sprite_holder/00_Group.Sprite_Holder_006_ilo_ 01_phase_00.png",
          "renderPath": "extracted_assets\\grp\\G_REC\\sprite_holder\\00_Group.Sprite_Holder_006_ilo_ 01_phase_00.png",
          "stillPath": null,
          "stillUrl": null,
          "width": 18,
          "height": 19,
          "frameCount": null,
          "offset": 42048,
          "name": "ilość 01",
          "id": 19,
          "definitionId": 6,
          "phaseAssets": [
            {
              "phase": 0,
              "path": "extracted_assets\\grp\\G_REC\\sprite_holder\\00_Group.Sprite_Holder_006_ilo_ 01_phase_00.png",
              "url": "../extracted_assets/grp/G_REC/sprite_holder/00_Group.Sprite_Holder_006_ilo_ 01_phase_00.png"
            },
            {
              "phase": 1,
              "path": "extracted_assets\\grp\\G_REC\\sprite_holder\\00_Group.Sprite_Holder_006_ilo_ 01_phase_01.png",
              "url": "../extracted_assets/grp/G_REC/sprite_holder/00_Group.Sprite_Holder_006_ilo_ 01_phase_01.png"
            },
            {
              "phase": 2,
              "path": "extracted_assets\\grp\\G_REC\\sprite_holder\\00_Group.Sprite_Holder_006_ilo_ 01_phase_02.png",
              "url": "../extracted_assets/grp/G_REC/sprite_holder/00_Group.Sprite_Holder_006_ilo_ 01_phase_02.png"
            },
            {
              "phase": 3,
              "path": "extracted_assets\\grp\\G_REC\\sprite_holder\\00_Group.Sprite_Holder_006_ilo_ 01_phase_03.png",
              "url": "../extracted_assets/grp/G_REC/sprite_holder/00_Group.Sprite_Holder_006_ilo_ 01_phase_03.png"
            },
            {
              "phase": 4,
              "path": "extracted_assets\\grp\\G_REC\\sprite_holder\\00_Group.Sprite_Holder_006_ilo_ 01_phase_04.png",
              "url": "../extracted_assets/grp/G_REC/sprite_holder/00_Group.Sprite_Holder_006_ilo_ 01_phase_04.png"
            }
          ],
          "phaseCount": 5,
          "instanceOffset": 152128,
          "rect": {
            "x": 240,
            "y": 460,
            "width": 18,
            "height": 19
          },
          "geometryConfidence": "serialized_instance",
          "initialPhase": 0,
          "initiallyVisible": true,
          "draggable": false,
          "z": 0
        },
        {
          "kind": "sprite_holder_png",
          "path": "extracted_assets\\grp\\G_REC\\sprite_holder\\00_Group.Sprite_Holder_006_ilo_ 01_phase_00.png",
          "url": "../extracted_assets/grp/G_REC/sprite_holder/00_Group.Sprite_Holder_006_ilo_ 01_phase_00.png",
          "renderPath": "extracted_assets\\grp\\G_REC\\sprite_holder\\00_Group.Sprite_Holder_006_ilo_ 01_phase_00.png",
          "stillPath": null,
          "stillUrl": null,
          "width": 18,
          "height": 19,
          "frameCount": null,
          "offset": 42048,
          "name": "ilość 01",
          "id": 20,
          "definitionId": 6,
          "phaseAssets": [
            {
              "phase": 0,
              "path": "extracted_assets\\grp\\G_REC\\sprite_holder\\00_Group.Sprite_Holder_006_ilo_ 01_phase_00.png",
              "url": "../extracted_assets/grp/G_REC/sprite_holder/00_Group.Sprite_Holder_006_ilo_ 01_phase_00.png"
            },
            {
              "phase": 1,
              "path": "extracted_assets\\grp\\G_REC\\sprite_holder\\00_Group.Sprite_Holder_006_ilo_ 01_phase_01.png",
              "url": "../extracted_assets/grp/G_REC/sprite_holder/00_Group.Sprite_Holder_006_ilo_ 01_phase_01.png"
            },
            {
              "phase": 2,
              "path": "extracted_assets\\grp\\G_REC\\sprite_holder\\00_Group.Sprite_Holder_006_ilo_ 01_phase_02.png",
              "url": "../extracted_assets/grp/G_REC/sprite_holder/00_Group.Sprite_Holder_006_ilo_ 01_phase_02.png"
            },
            {
              "phase": 3,
              "path": "extracted_assets\\grp\\G_REC\\sprite_holder\\00_Group.Sprite_Holder_006_ilo_ 01_phase_03.png",
              "url": "../extracted_assets/grp/G_REC/sprite_holder/00_Group.Sprite_Holder_006_ilo_ 01_phase_03.png"
            },
            {
              "phase": 4,
              "path": "extracted_assets\\grp\\G_REC\\sprite_holder\\00_Group.Sprite_Holder_006_ilo_ 01_phase_04.png",
              "url": "../extracted_assets/grp/G_REC/sprite_holder/00_Group.Sprite_Holder_006_ilo_ 01_phase_04.png"
            }
          ],
          "phaseCount": 5,
          "instanceOffset": 152268,
          "rect": {
            "x": 259,
            "y": 460,
            "width": 18,
            "height": 19
          },
          "geometryConfidence": "serialized_instance",
          "initialPhase": 0,
          "initiallyVisible": true,
          "draggable": false,
          "z": 0
        },
        {
          "kind": "sprite_holder_png",
          "path": "extracted_assets\\grp\\G_REC\\sprite_holder\\00_Group.Sprite_Holder_006_ilo_ 01_phase_00.png",
          "url": "../extracted_assets/grp/G_REC/sprite_holder/00_Group.Sprite_Holder_006_ilo_ 01_phase_00.png",
          "renderPath": "extracted_assets\\grp\\G_REC\\sprite_holder\\00_Group.Sprite_Holder_006_ilo_ 01_phase_00.png",
          "stillPath": null,
          "stillUrl": null,
          "width": 18,
          "height": 19,
          "frameCount": null,
          "offset": 42048,
          "name": "ilość 01",
          "id": 21,
          "definitionId": 6,
          "phaseAssets": [
            {
              "phase": 0,
              "path": "extracted_assets\\grp\\G_REC\\sprite_holder\\00_Group.Sprite_Holder_006_ilo_ 01_phase_00.png",
              "url": "../extracted_assets/grp/G_REC/sprite_holder/00_Group.Sprite_Holder_006_ilo_ 01_phase_00.png"
            },
            {
              "phase": 1,
              "path": "extracted_assets\\grp\\G_REC\\sprite_holder\\00_Group.Sprite_Holder_006_ilo_ 01_phase_01.png",
              "url": "../extracted_assets/grp/G_REC/sprite_holder/00_Group.Sprite_Holder_006_ilo_ 01_phase_01.png"
            },
            {
              "phase": 2,
              "path": "extracted_assets\\grp\\G_REC\\sprite_holder\\00_Group.Sprite_Holder_006_ilo_ 01_phase_02.png",
              "url": "../extracted_assets/grp/G_REC/sprite_holder/00_Group.Sprite_Holder_006_ilo_ 01_phase_02.png"
            },
            {
              "phase": 3,
              "path": "extracted_assets\\grp\\G_REC\\sprite_holder\\00_Group.Sprite_Holder_006_ilo_ 01_phase_03.png",
              "url": "../extracted_assets/grp/G_REC/sprite_holder/00_Group.Sprite_Holder_006_ilo_ 01_phase_03.png"
            },
            {
              "phase": 4,
              "path": "extracted_assets\\grp\\G_REC\\sprite_holder\\00_Group.Sprite_Holder_006_ilo_ 01_phase_04.png",
              "url": "../extracted_assets/grp/G_REC/sprite_holder/00_Group.Sprite_Holder_006_ilo_ 01_phase_04.png"
            }
          ],
          "phaseCount": 5,
          "instanceOffset": 152408,
          "rect": {
            "x": 278,
            "y": 460,
            "width": 18,
            "height": 19
          },
          "geometryConfidence": "serialized_instance",
          "initialPhase": 0,
          "initiallyVisible": true,
          "draggable": false,
          "z": 0
        },
        {
          "kind": "sprite_holder_png",
          "path": "extracted_assets\\grp\\G_REC\\sprite_holder\\00_Group.Sprite_Holder_006_ilo_ 01_phase_00.png",
          "url": "../extracted_assets/grp/G_REC/sprite_holder/00_Group.Sprite_Holder_006_ilo_ 01_phase_00.png",
          "renderPath": "extracted_assets\\grp\\G_REC\\sprite_holder\\00_Group.Sprite_Holder_006_ilo_ 01_phase_00.png",
          "stillPath": null,
          "stillUrl": null,
          "width": 18,
          "height": 19,
          "frameCount": null,
          "offset": 42048,
          "name": "ilość 01",
          "id": 22,
          "definitionId": 6,
          "phaseAssets": [
            {
              "phase": 0,
              "path": "extracted_assets\\grp\\G_REC\\sprite_holder\\00_Group.Sprite_Holder_006_ilo_ 01_phase_00.png",
              "url": "../extracted_assets/grp/G_REC/sprite_holder/00_Group.Sprite_Holder_006_ilo_ 01_phase_00.png"
            },
            {
              "phase": 1,
              "path": "extracted_assets\\grp\\G_REC\\sprite_holder\\00_Group.Sprite_Holder_006_ilo_ 01_phase_01.png",
              "url": "../extracted_assets/grp/G_REC/sprite_holder/00_Group.Sprite_Holder_006_ilo_ 01_phase_01.png"
            },
            {
              "phase": 2,
              "path": "extracted_assets\\grp\\G_REC\\sprite_holder\\00_Group.Sprite_Holder_006_ilo_ 01_phase_02.png",
              "url": "../extracted_assets/grp/G_REC/sprite_holder/00_Group.Sprite_Holder_006_ilo_ 01_phase_02.png"
            },
            {
              "phase": 3,
              "path": "extracted_assets\\grp\\G_REC\\sprite_holder\\00_Group.Sprite_Holder_006_ilo_ 01_phase_03.png",
              "url": "../extracted_assets/grp/G_REC/sprite_holder/00_Group.Sprite_Holder_006_ilo_ 01_phase_03.png"
            },
            {
              "phase": 4,
              "path": "extracted_assets\\grp\\G_REC\\sprite_holder\\00_Group.Sprite_Holder_006_ilo_ 01_phase_04.png",
              "url": "../extracted_assets/grp/G_REC/sprite_holder/00_Group.Sprite_Holder_006_ilo_ 01_phase_04.png"
            }
          ],
          "phaseCount": 5,
          "instanceOffset": 152548,
          "rect": {
            "x": 297,
            "y": 460,
            "width": 18,
            "height": 19
          },
          "geometryConfidence": "serialized_instance",
          "initialPhase": 0,
          "initiallyVisible": true,
          "draggable": false,
          "z": 0
        },
        {
          "kind": "sprite_holder_png",
          "path": "extracted_assets\\grp\\G_REC\\sprite_holder\\00_Group.Sprite_Holder_006_ilo_ 01_phase_00.png",
          "url": "../extracted_assets/grp/G_REC/sprite_holder/00_Group.Sprite_Holder_006_ilo_ 01_phase_00.png",
          "renderPath": "extracted_assets\\grp\\G_REC\\sprite_holder\\00_Group.Sprite_Holder_006_ilo_ 01_phase_00.png",
          "stillPath": null,
          "stillUrl": null,
          "width": 18,
          "height": 19,
          "frameCount": null,
          "offset": 42048,
          "name": "ilość 01",
          "id": 23,
          "definitionId": 6,
          "phaseAssets": [
            {
              "phase": 0,
              "path": "extracted_assets\\grp\\G_REC\\sprite_holder\\00_Group.Sprite_Holder_006_ilo_ 01_phase_00.png",
              "url": "../extracted_assets/grp/G_REC/sprite_holder/00_Group.Sprite_Holder_006_ilo_ 01_phase_00.png"
            },
            {
              "phase": 1,
              "path": "extracted_assets\\grp\\G_REC\\sprite_holder\\00_Group.Sprite_Holder_006_ilo_ 01_phase_01.png",
              "url": "../extracted_assets/grp/G_REC/sprite_holder/00_Group.Sprite_Holder_006_ilo_ 01_phase_01.png"
            },
            {
              "phase": 2,
              "path": "extracted_assets\\grp\\G_REC\\sprite_holder\\00_Group.Sprite_Holder_006_ilo_ 01_phase_02.png",
              "url": "../extracted_assets/grp/G_REC/sprite_holder/00_Group.Sprite_Holder_006_ilo_ 01_phase_02.png"
            },
            {
              "phase": 3,
              "path": "extracted_assets\\grp\\G_REC\\sprite_holder\\00_Group.Sprite_Holder_006_ilo_ 01_phase_03.png",
              "url": "../extracted_assets/grp/G_REC/sprite_holder/00_Group.Sprite_Holder_006_ilo_ 01_phase_03.png"
            },
            {
              "phase": 4,
              "path": "extracted_assets\\grp\\G_REC\\sprite_holder\\00_Group.Sprite_Holder_006_ilo_ 01_phase_04.png",
              "url": "../extracted_assets/grp/G_REC/sprite_holder/00_Group.Sprite_Holder_006_ilo_ 01_phase_04.png"
            }
          ],
          "phaseCount": 5,
          "instanceOffset": 152688,
          "rect": {
            "x": 316,
            "y": 460,
            "width": 18,
            "height": 19
          },
          "geometryConfidence": "serialized_instance",
          "initialPhase": 0,
          "initiallyVisible": true,
          "draggable": false,
          "z": 0
        },
        {
          "kind": "sprite_holder_png",
          "path": "extracted_assets\\grp\\G_REC\\sprite_holder\\00_Group.Sprite_Holder_006_ilo_ 01_phase_00.png",
          "url": "../extracted_assets/grp/G_REC/sprite_holder/00_Group.Sprite_Holder_006_ilo_ 01_phase_00.png",
          "renderPath": "extracted_assets\\grp\\G_REC\\sprite_holder\\00_Group.Sprite_Holder_006_ilo_ 01_phase_00.png",
          "stillPath": null,
          "stillUrl": null,
          "width": 18,
          "height": 19,
          "frameCount": null,
          "offset": 42048,
          "name": "ilość 01",
          "id": 24,
          "definitionId": 6,
          "phaseAssets": [
            {
              "phase": 0,
              "path": "extracted_assets\\grp\\G_REC\\sprite_holder\\00_Group.Sprite_Holder_006_ilo_ 01_phase_00.png",
              "url": "../extracted_assets/grp/G_REC/sprite_holder/00_Group.Sprite_Holder_006_ilo_ 01_phase_00.png"
            },
            {
              "phase": 1,
              "path": "extracted_assets\\grp\\G_REC\\sprite_holder\\00_Group.Sprite_Holder_006_ilo_ 01_phase_01.png",
              "url": "../extracted_assets/grp/G_REC/sprite_holder/00_Group.Sprite_Holder_006_ilo_ 01_phase_01.png"
            },
            {
              "phase": 2,
              "path": "extracted_assets\\grp\\G_REC\\sprite_holder\\00_Group.Sprite_Holder_006_ilo_ 01_phase_02.png",
              "url": "../extracted_assets/grp/G_REC/sprite_holder/00_Group.Sprite_Holder_006_ilo_ 01_phase_02.png"
            },
            {
              "phase": 3,
              "path": "extracted_assets\\grp\\G_REC\\sprite_holder\\00_Group.Sprite_Holder_006_ilo_ 01_phase_03.png",
              "url": "../extracted_assets/grp/G_REC/sprite_holder/00_Group.Sprite_Holder_006_ilo_ 01_phase_03.png"
            },
            {
              "phase": 4,
              "path": "extracted_assets\\grp\\G_REC\\sprite_holder\\00_Group.Sprite_Holder_006_ilo_ 01_phase_04.png",
              "url": "../extracted_assets/grp/G_REC/sprite_holder/00_Group.Sprite_Holder_006_ilo_ 01_phase_04.png"
            }
          ],
          "phaseCount": 5,
          "instanceOffset": 152828,
          "rect": {
            "x": 335,
            "y": 460,
            "width": 18,
            "height": 19
          },
          "geometryConfidence": "serialized_instance",
          "initialPhase": 0,
          "initiallyVisible": true,
          "draggable": false,
          "z": 0
        },
        {
          "kind": "sprite_holder_png",
          "path": "extracted_assets\\grp\\G_REC\\sprite_holder\\00_Group.Sprite_Holder_006_ilo_ 01_phase_00.png",
          "url": "../extracted_assets/grp/G_REC/sprite_holder/00_Group.Sprite_Holder_006_ilo_ 01_phase_00.png",
          "renderPath": "extracted_assets\\grp\\G_REC\\sprite_holder\\00_Group.Sprite_Holder_006_ilo_ 01_phase_00.png",
          "stillPath": null,
          "stillUrl": null,
          "width": 18,
          "height": 19,
          "frameCount": null,
          "offset": 42048,
          "name": "ilość 01",
          "id": 25,
          "definitionId": 6,
          "phaseAssets": [
            {
              "phase": 0,
              "path": "extracted_assets\\grp\\G_REC\\sprite_holder\\00_Group.Sprite_Holder_006_ilo_ 01_phase_00.png",
              "url": "../extracted_assets/grp/G_REC/sprite_holder/00_Group.Sprite_Holder_006_ilo_ 01_phase_00.png"
            },
            {
              "phase": 1,
              "path": "extracted_assets\\grp\\G_REC\\sprite_holder\\00_Group.Sprite_Holder_006_ilo_ 01_phase_01.png",
              "url": "../extracted_assets/grp/G_REC/sprite_holder/00_Group.Sprite_Holder_006_ilo_ 01_phase_01.png"
            },
            {
              "phase": 2,
              "path": "extracted_assets\\grp\\G_REC\\sprite_holder\\00_Group.Sprite_Holder_006_ilo_ 01_phase_02.png",
              "url": "../extracted_assets/grp/G_REC/sprite_holder/00_Group.Sprite_Holder_006_ilo_ 01_phase_02.png"
            },
            {
              "phase": 3,
              "path": "extracted_assets\\grp\\G_REC\\sprite_holder\\00_Group.Sprite_Holder_006_ilo_ 01_phase_03.png",
              "url": "../extracted_assets/grp/G_REC/sprite_holder/00_Group.Sprite_Holder_006_ilo_ 01_phase_03.png"
            },
            {
              "phase": 4,
              "path": "extracted_assets\\grp\\G_REC\\sprite_holder\\00_Group.Sprite_Holder_006_ilo_ 01_phase_04.png",
              "url": "../extracted_assets/grp/G_REC/sprite_holder/00_Group.Sprite_Holder_006_ilo_ 01_phase_04.png"
            }
          ],
          "phaseCount": 5,
          "instanceOffset": 152968,
          "rect": {
            "x": 354,
            "y": 460,
            "width": 18,
            "height": 19
          },
          "geometryConfidence": "serialized_instance",
          "initialPhase": 0,
          "initiallyVisible": true,
          "draggable": false,
          "z": 0
        },
        {
          "kind": "sprite_holder_png",
          "path": "extracted_assets\\grp\\G_REC\\sprite_holder\\00_Group.Sprite_Holder_006_ilo_ 01_phase_00.png",
          "url": "../extracted_assets/grp/G_REC/sprite_holder/00_Group.Sprite_Holder_006_ilo_ 01_phase_00.png",
          "renderPath": "extracted_assets\\grp\\G_REC\\sprite_holder\\00_Group.Sprite_Holder_006_ilo_ 01_phase_00.png",
          "stillPath": null,
          "stillUrl": null,
          "width": 18,
          "height": 19,
          "frameCount": null,
          "offset": 42048,
          "name": "ilość 01",
          "id": 26,
          "definitionId": 6,
          "phaseAssets": [
            {
              "phase": 0,
              "path": "extracted_assets\\grp\\G_REC\\sprite_holder\\00_Group.Sprite_Holder_006_ilo_ 01_phase_00.png",
              "url": "../extracted_assets/grp/G_REC/sprite_holder/00_Group.Sprite_Holder_006_ilo_ 01_phase_00.png"
            },
            {
              "phase": 1,
              "path": "extracted_assets\\grp\\G_REC\\sprite_holder\\00_Group.Sprite_Holder_006_ilo_ 01_phase_01.png",
              "url": "../extracted_assets/grp/G_REC/sprite_holder/00_Group.Sprite_Holder_006_ilo_ 01_phase_01.png"
            },
            {
              "phase": 2,
              "path": "extracted_assets\\grp\\G_REC\\sprite_holder\\00_Group.Sprite_Holder_006_ilo_ 01_phase_02.png",
              "url": "../extracted_assets/grp/G_REC/sprite_holder/00_Group.Sprite_Holder_006_ilo_ 01_phase_02.png"
            },
            {
              "phase": 3,
              "path": "extracted_assets\\grp\\G_REC\\sprite_holder\\00_Group.Sprite_Holder_006_ilo_ 01_phase_03.png",
              "url": "../extracted_assets/grp/G_REC/sprite_holder/00_Group.Sprite_Holder_006_ilo_ 01_phase_03.png"
            },
            {
              "phase": 4,
              "path": "extracted_assets\\grp\\G_REC\\sprite_holder\\00_Group.Sprite_Holder_006_ilo_ 01_phase_04.png",
              "url": "../extracted_assets/grp/G_REC/sprite_holder/00_Group.Sprite_Holder_006_ilo_ 01_phase_04.png"
            }
          ],
          "phaseCount": 5,
          "instanceOffset": 153108,
          "rect": {
            "x": 373,
            "y": 460,
            "width": 18,
            "height": 19
          },
          "geometryConfidence": "serialized_instance",
          "initialPhase": 0,
          "initiallyVisible": true,
          "draggable": false,
          "z": 0
        },
        {
          "kind": "sprite_holder_png",
          "path": "extracted_assets\\grp\\G_REC\\sprite_holder\\00_Group.Sprite_Holder_006_ilo_ 01_phase_00.png",
          "url": "../extracted_assets/grp/G_REC/sprite_holder/00_Group.Sprite_Holder_006_ilo_ 01_phase_00.png",
          "renderPath": "extracted_assets\\grp\\G_REC\\sprite_holder\\00_Group.Sprite_Holder_006_ilo_ 01_phase_00.png",
          "stillPath": null,
          "stillUrl": null,
          "width": 18,
          "height": 19,
          "frameCount": null,
          "offset": 42048,
          "name": "ilość 01",
          "id": 27,
          "definitionId": 6,
          "phaseAssets": [
            {
              "phase": 0,
              "path": "extracted_assets\\grp\\G_REC\\sprite_holder\\00_Group.Sprite_Holder_006_ilo_ 01_phase_00.png",
              "url": "../extracted_assets/grp/G_REC/sprite_holder/00_Group.Sprite_Holder_006_ilo_ 01_phase_00.png"
            },
            {
              "phase": 1,
              "path": "extracted_assets\\grp\\G_REC\\sprite_holder\\00_Group.Sprite_Holder_006_ilo_ 01_phase_01.png",
              "url": "../extracted_assets/grp/G_REC/sprite_holder/00_Group.Sprite_Holder_006_ilo_ 01_phase_01.png"
            },
            {
              "phase": 2,
              "path": "extracted_assets\\grp\\G_REC\\sprite_holder\\00_Group.Sprite_Holder_006_ilo_ 01_phase_02.png",
              "url": "../extracted_assets/grp/G_REC/sprite_holder/00_Group.Sprite_Holder_006_ilo_ 01_phase_02.png"
            },
            {
              "phase": 3,
              "path": "extracted_assets\\grp\\G_REC\\sprite_holder\\00_Group.Sprite_Holder_006_ilo_ 01_phase_03.png",
              "url": "../extracted_assets/grp/G_REC/sprite_holder/00_Group.Sprite_Holder_006_ilo_ 01_phase_03.png"
            },
            {
              "phase": 4,
              "path": "extracted_assets\\grp\\G_REC\\sprite_holder\\00_Group.Sprite_Holder_006_ilo_ 01_phase_04.png",
              "url": "../extracted_assets/grp/G_REC/sprite_holder/00_Group.Sprite_Holder_006_ilo_ 01_phase_04.png"
            }
          ],
          "phaseCount": 5,
          "instanceOffset": 153248,
          "rect": {
            "x": 392,
            "y": 460,
            "width": 18,
            "height": 19
          },
          "geometryConfidence": "serialized_instance",
          "initialPhase": 0,
          "initiallyVisible": true,
          "draggable": false,
          "z": 0
        },
        {
          "kind": "sprite_holder_png",
          "path": "extracted_assets\\grp\\G_REC\\sprite_holder\\00_Group.Sprite_Holder_006_ilo_ 01_phase_00.png",
          "url": "../extracted_assets/grp/G_REC/sprite_holder/00_Group.Sprite_Holder_006_ilo_ 01_phase_00.png",
          "renderPath": "extracted_assets\\grp\\G_REC\\sprite_holder\\00_Group.Sprite_Holder_006_ilo_ 01_phase_00.png",
          "stillPath": null,
          "stillUrl": null,
          "width": 18,
          "height": 19,
          "frameCount": null,
          "offset": 42048,
          "name": "ilość 01",
          "id": 28,
          "definitionId": 6,
          "phaseAssets": [
            {
              "phase": 0,
              "path": "extracted_assets\\grp\\G_REC\\sprite_holder\\00_Group.Sprite_Holder_006_ilo_ 01_phase_00.png",
              "url": "../extracted_assets/grp/G_REC/sprite_holder/00_Group.Sprite_Holder_006_ilo_ 01_phase_00.png"
            },
            {
              "phase": 1,
              "path": "extracted_assets\\grp\\G_REC\\sprite_holder\\00_Group.Sprite_Holder_006_ilo_ 01_phase_01.png",
              "url": "../extracted_assets/grp/G_REC/sprite_holder/00_Group.Sprite_Holder_006_ilo_ 01_phase_01.png"
            },
            {
              "phase": 2,
              "path": "extracted_assets\\grp\\G_REC\\sprite_holder\\00_Group.Sprite_Holder_006_ilo_ 01_phase_02.png",
              "url": "../extracted_assets/grp/G_REC/sprite_holder/00_Group.Sprite_Holder_006_ilo_ 01_phase_02.png"
            },
            {
              "phase": 3,
              "path": "extracted_assets\\grp\\G_REC\\sprite_holder\\00_Group.Sprite_Holder_006_ilo_ 01_phase_03.png",
              "url": "../extracted_assets/grp/G_REC/sprite_holder/00_Group.Sprite_Holder_006_ilo_ 01_phase_03.png"
            },
            {
              "phase": 4,
              "path": "extracted_assets\\grp\\G_REC\\sprite_holder\\00_Group.Sprite_Holder_006_ilo_ 01_phase_04.png",
              "url": "../extracted_assets/grp/G_REC/sprite_holder/00_Group.Sprite_Holder_006_ilo_ 01_phase_04.png"
            }
          ],
          "phaseCount": 5,
          "instanceOffset": 153388,
          "rect": {
            "x": 411,
            "y": 460,
            "width": 18,
            "height": 19
          },
          "geometryConfidence": "serialized_instance",
          "initialPhase": 0,
          "initiallyVisible": true,
          "draggable": false,
          "z": 0
        },
        {
          "kind": "sprite_holder_png",
          "path": "extracted_assets\\grp\\G_REC\\sprite_holder\\00_Group.Sprite_Holder_006_ilo_ 01_phase_00.png",
          "url": "../extracted_assets/grp/G_REC/sprite_holder/00_Group.Sprite_Holder_006_ilo_ 01_phase_00.png",
          "renderPath": "extracted_assets\\grp\\G_REC\\sprite_holder\\00_Group.Sprite_Holder_006_ilo_ 01_phase_00.png",
          "stillPath": null,
          "stillUrl": null,
          "width": 18,
          "height": 19,
          "frameCount": null,
          "offset": 42048,
          "name": "ilość 01",
          "id": 29,
          "definitionId": 6,
          "phaseAssets": [
            {
              "phase": 0,
              "path": "extracted_assets\\grp\\G_REC\\sprite_holder\\00_Group.Sprite_Holder_006_ilo_ 01_phase_00.png",
              "url": "../extracted_assets/grp/G_REC/sprite_holder/00_Group.Sprite_Holder_006_ilo_ 01_phase_00.png"
            },
            {
              "phase": 1,
              "path": "extracted_assets\\grp\\G_REC\\sprite_holder\\00_Group.Sprite_Holder_006_ilo_ 01_phase_01.png",
              "url": "../extracted_assets/grp/G_REC/sprite_holder/00_Group.Sprite_Holder_006_ilo_ 01_phase_01.png"
            },
            {
              "phase": 2,
              "path": "extracted_assets\\grp\\G_REC\\sprite_holder\\00_Group.Sprite_Holder_006_ilo_ 01_phase_02.png",
              "url": "../extracted_assets/grp/G_REC/sprite_holder/00_Group.Sprite_Holder_006_ilo_ 01_phase_02.png"
            },
            {
              "phase": 3,
              "path": "extracted_assets\\grp\\G_REC\\sprite_holder\\00_Group.Sprite_Holder_006_ilo_ 01_phase_03.png",
              "url": "../extracted_assets/grp/G_REC/sprite_holder/00_Group.Sprite_Holder_006_ilo_ 01_phase_03.png"
            },
            {
              "phase": 4,
              "path": "extracted_assets\\grp\\G_REC\\sprite_holder\\00_Group.Sprite_Holder_006_ilo_ 01_phase_04.png",
              "url": "../extracted_assets/grp/G_REC/sprite_holder/00_Group.Sprite_Holder_006_ilo_ 01_phase_04.png"
            }
          ],
          "phaseCount": 5,
          "instanceOffset": 153528,
          "rect": {
            "x": 429,
            "y": 460,
            "width": 18,
            "height": 19
          },
          "geometryConfidence": "serialized_instance",
          "initialPhase": 0,
          "initiallyVisible": true,
          "draggable": false,
          "z": 0
        },
        {
          "kind": "sprite_holder_png",
          "path": "extracted_assets\\grp\\G_REC\\sprite_holder\\00_Group.Sprite_Holder_006_ilo_ 01_phase_00.png",
          "url": "../extracted_assets/grp/G_REC/sprite_holder/00_Group.Sprite_Holder_006_ilo_ 01_phase_00.png",
          "renderPath": "extracted_assets\\grp\\G_REC\\sprite_holder\\00_Group.Sprite_Holder_006_ilo_ 01_phase_00.png",
          "stillPath": null,
          "stillUrl": null,
          "width": 18,
          "height": 19,
          "frameCount": null,
          "offset": 42048,
          "name": "ilość 01",
          "id": 30,
          "definitionId": 6,
          "phaseAssets": [
            {
              "phase": 0,
              "path": "extracted_assets\\grp\\G_REC\\sprite_holder\\00_Group.Sprite_Holder_006_ilo_ 01_phase_00.png",
              "url": "../extracted_assets/grp/G_REC/sprite_holder/00_Group.Sprite_Holder_006_ilo_ 01_phase_00.png"
            },
            {
              "phase": 1,
              "path": "extracted_assets\\grp\\G_REC\\sprite_holder\\00_Group.Sprite_Holder_006_ilo_ 01_phase_01.png",
              "url": "../extracted_assets/grp/G_REC/sprite_holder/00_Group.Sprite_Holder_006_ilo_ 01_phase_01.png"
            },
            {
              "phase": 2,
              "path": "extracted_assets\\grp\\G_REC\\sprite_holder\\00_Group.Sprite_Holder_006_ilo_ 01_phase_02.png",
              "url": "../extracted_assets/grp/G_REC/sprite_holder/00_Group.Sprite_Holder_006_ilo_ 01_phase_02.png"
            },
            {
              "phase": 3,
              "path": "extracted_assets\\grp\\G_REC\\sprite_holder\\00_Group.Sprite_Holder_006_ilo_ 01_phase_03.png",
              "url": "../extracted_assets/grp/G_REC/sprite_holder/00_Group.Sprite_Holder_006_ilo_ 01_phase_03.png"
            },
            {
              "phase": 4,
              "path": "extracted_assets\\grp\\G_REC\\sprite_holder\\00_Group.Sprite_Holder_006_ilo_ 01_phase_04.png",
              "url": "../extracted_assets/grp/G_REC/sprite_holder/00_Group.Sprite_Holder_006_ilo_ 01_phase_04.png"
            }
          ],
          "phaseCount": 5,
          "instanceOffset": 153668,
          "rect": {
            "x": 448,
            "y": 460,
            "width": 18,
            "height": 19
          },
          "geometryConfidence": "serialized_instance",
          "initialPhase": 0,
          "initiallyVisible": true,
          "draggable": false,
          "z": 0
        },
        {
          "kind": "sprite_holder_png",
          "path": "extracted_assets\\grp\\G_REC\\sprite_holder\\00_Group.Sprite_Holder_006_ilo_ 01_phase_00.png",
          "url": "../extracted_assets/grp/G_REC/sprite_holder/00_Group.Sprite_Holder_006_ilo_ 01_phase_00.png",
          "renderPath": "extracted_assets\\grp\\G_REC\\sprite_holder\\00_Group.Sprite_Holder_006_ilo_ 01_phase_00.png",
          "stillPath": null,
          "stillUrl": null,
          "width": 18,
          "height": 19,
          "frameCount": null,
          "offset": 42048,
          "name": "ilość 01",
          "id": 31,
          "definitionId": 6,
          "phaseAssets": [
            {
              "phase": 0,
              "path": "extracted_assets\\grp\\G_REC\\sprite_holder\\00_Group.Sprite_Holder_006_ilo_ 01_phase_00.png",
              "url": "../extracted_assets/grp/G_REC/sprite_holder/00_Group.Sprite_Holder_006_ilo_ 01_phase_00.png"
            },
            {
              "phase": 1,
              "path": "extracted_assets\\grp\\G_REC\\sprite_holder\\00_Group.Sprite_Holder_006_ilo_ 01_phase_01.png",
              "url": "../extracted_assets/grp/G_REC/sprite_holder/00_Group.Sprite_Holder_006_ilo_ 01_phase_01.png"
            },
            {
              "phase": 2,
              "path": "extracted_assets\\grp\\G_REC\\sprite_holder\\00_Group.Sprite_Holder_006_ilo_ 01_phase_02.png",
              "url": "../extracted_assets/grp/G_REC/sprite_holder/00_Group.Sprite_Holder_006_ilo_ 01_phase_02.png"
            },
            {
              "phase": 3,
              "path": "extracted_assets\\grp\\G_REC\\sprite_holder\\00_Group.Sprite_Holder_006_ilo_ 01_phase_03.png",
              "url": "../extracted_assets/grp/G_REC/sprite_holder/00_Group.Sprite_Holder_006_ilo_ 01_phase_03.png"
            },
            {
              "phase": 4,
              "path": "extracted_assets\\grp\\G_REC\\sprite_holder\\00_Group.Sprite_Holder_006_ilo_ 01_phase_04.png",
              "url": "../extracted_assets/grp/G_REC/sprite_holder/00_Group.Sprite_Holder_006_ilo_ 01_phase_04.png"
            }
          ],
          "phaseCount": 5,
          "instanceOffset": 153808,
          "rect": {
            "x": 467,
            "y": 460,
            "width": 18,
            "height": 19
          },
          "geometryConfidence": "serialized_instance",
          "initialPhase": 0,
          "initiallyVisible": true,
          "draggable": false,
          "z": 0
        },
        {
          "kind": "sprite_holder_png",
          "path": "extracted_assets\\grp\\G_REC\\sprite_holder\\00_Group.Sprite_Holder_007_toolbar_phase_00.png",
          "url": "../extracted_assets/grp/G_REC/sprite_holder/00_Group.Sprite_Holder_007_toolbar_phase_00.png",
          "renderPath": "extracted_assets\\grp\\G_REC\\sprite_holder\\00_Group.Sprite_Holder_007_toolbar_phase_00.png",
          "stillPath": null,
          "stillUrl": null,
          "width": 160,
          "height": 480,
          "frameCount": null,
          "offset": 44520,
          "name": "toolbar",
          "id": 32,
          "definitionId": 7,
          "phaseAssets": [
            {
              "phase": 0,
              "path": "extracted_assets\\grp\\G_REC\\sprite_holder\\00_Group.Sprite_Holder_007_toolbar_phase_00.png",
              "url": "../extracted_assets/grp/G_REC/sprite_holder/00_Group.Sprite_Holder_007_toolbar_phase_00.png"
            }
          ],
          "phaseCount": 1,
          "instanceOffset": 153948,
          "rect": {
            "x": 640,
            "y": 0,
            "width": 160,
            "height": 480
          },
          "geometryConfidence": "serialized_instance",
          "initialPhase": 0,
          "initiallyVisible": true,
          "draggable": false,
          "z": 5
        },
        {
          "kind": "sprite_holder_png",
          "path": "extracted_assets\\grp\\G_REC\\sprite_holder\\00_Group.Sprite_Holder_008_strza_ka_phase_00.png",
          "url": "../extracted_assets/grp/G_REC/sprite_holder/00_Group.Sprite_Holder_008_strza_ka_phase_00.png",
          "renderPath": "extracted_assets\\grp\\G_REC\\sprite_holder\\00_Group.Sprite_Holder_008_strza_ka_phase_00.png",
          "stillPath": null,
          "stillUrl": null,
          "width": 66,
          "height": 61,
          "frameCount": null,
          "offset": 121588,
          "name": "strzałka ",
          "id": 33,
          "definitionId": 8,
          "phaseAssets": [
            {
              "phase": 0,
              "path": "extracted_assets\\grp\\G_REC\\sprite_holder\\00_Group.Sprite_Holder_008_strza_ka_phase_00.png",
              "url": "../extracted_assets/grp/G_REC/sprite_holder/00_Group.Sprite_Holder_008_strza_ka_phase_00.png"
            },
            {
              "phase": 1,
              "path": "extracted_assets\\grp\\G_REC\\sprite_holder\\00_Group.Sprite_Holder_008_strza_ka_phase_01.png",
              "url": "../extracted_assets/grp/G_REC/sprite_holder/00_Group.Sprite_Holder_008_strza_ka_phase_01.png"
            }
          ],
          "phaseCount": 2,
          "instanceOffset": 154088,
          "rect": {
            "x": 721,
            "y": 329,
            "width": 66,
            "height": 61
          },
          "geometryConfidence": "serialized_instance",
          "initialPhase": 0,
          "initiallyVisible": true,
          "draggable": false,
          "z": 6
        },
        {
          "kind": "sprite_holder_png",
          "path": "extracted_assets\\grp\\G_REC\\sprite_holder\\00_Group.Sprite_Holder_009_wyb_r 01_phase_00.png",
          "url": "../extracted_assets/grp/G_REC/sprite_holder/00_Group.Sprite_Holder_009_wyb_r 01_phase_00.png",
          "renderPath": "extracted_assets\\grp\\G_REC\\sprite_holder\\00_Group.Sprite_Holder_009_wyb_r 01_phase_00.png",
          "stillPath": null,
          "stillUrl": null,
          "width": 77,
          "height": 64,
          "frameCount": null,
          "offset": 130152,
          "name": "wybór 01",
          "id": 34,
          "definitionId": 9,
          "phaseAssets": [
            {
              "phase": 0,
              "path": "extracted_assets\\grp\\G_REC\\sprite_holder\\00_Group.Sprite_Holder_009_wyb_r 01_phase_00.png",
              "url": "../extracted_assets/grp/G_REC/sprite_holder/00_Group.Sprite_Holder_009_wyb_r 01_phase_00.png"
            },
            {
              "phase": 1,
              "path": "extracted_assets\\grp\\G_REC\\sprite_holder\\00_Group.Sprite_Holder_009_wyb_r 01_phase_01.png",
              "url": "../extracted_assets/grp/G_REC/sprite_holder/00_Group.Sprite_Holder_009_wyb_r 01_phase_01.png"
            }
          ],
          "phaseCount": 2,
          "instanceOffset": 154228,
          "rect": {
            "x": 717,
            "y": 404,
            "width": 77,
            "height": 64
          },
          "geometryConfidence": "serialized_instance",
          "initialPhase": 0,
          "initiallyVisible": true,
          "draggable": false,
          "z": 6
        },
        {
          "kind": "sprite_holder_png",
          "path": "extracted_assets\\grp\\G_REC\\sprite_holder\\00_Group.Sprite_Holder_010_strza_ka_phase_00.png",
          "url": "../extracted_assets/grp/G_REC/sprite_holder/00_Group.Sprite_Holder_010_strza_ka_phase_00.png",
          "renderPath": "extracted_assets\\grp\\G_REC\\sprite_holder\\00_Group.Sprite_Holder_010_strza_ka_phase_00.png",
          "stillPath": null,
          "stillUrl": null,
          "width": 40,
          "height": 49,
          "frameCount": null,
          "offset": 140736,
          "name": "strzałka ",
          "id": 35,
          "definitionId": 10,
          "phaseAssets": [
            {
              "phase": 0,
              "path": "extracted_assets\\grp\\G_REC\\sprite_holder\\00_Group.Sprite_Holder_010_strza_ka_phase_00.png",
              "url": "../extracted_assets/grp/G_REC/sprite_holder/00_Group.Sprite_Holder_010_strza_ka_phase_00.png"
            },
            {
              "phase": 1,
              "path": "extracted_assets\\grp\\G_REC\\sprite_holder\\00_Group.Sprite_Holder_010_strza_ka_phase_01.png",
              "url": "../extracted_assets/grp/G_REC/sprite_holder/00_Group.Sprite_Holder_010_strza_ka_phase_01.png"
            }
          ],
          "phaseCount": 2,
          "instanceOffset": 154368,
          "rect": {
            "x": 704,
            "y": 14,
            "width": 40,
            "height": 49
          },
          "geometryConfidence": "serialized_instance",
          "initialPhase": 0,
          "initiallyVisible": true,
          "draggable": false,
          "z": 8
        },
        {
          "kind": "sprite_holder_png",
          "path": "extracted_assets\\grp\\G_REC\\sprite_holder\\00_Group.Sprite_Holder_011_strza_ka_phase_00.png",
          "url": "../extracted_assets/grp/G_REC/sprite_holder/00_Group.Sprite_Holder_011_strza_ka_phase_00.png",
          "renderPath": "extracted_assets\\grp\\G_REC\\sprite_holder\\00_Group.Sprite_Holder_011_strza_ka_phase_00.png",
          "stillPath": null,
          "stillUrl": null,
          "width": 41,
          "height": 49,
          "frameCount": null,
          "offset": 145000,
          "name": "strzałka ",
          "id": 36,
          "definitionId": 11,
          "phaseAssets": [
            {
              "phase": 0,
              "path": "extracted_assets\\grp\\G_REC\\sprite_holder\\00_Group.Sprite_Holder_011_strza_ka_phase_00.png",
              "url": "../extracted_assets/grp/G_REC/sprite_holder/00_Group.Sprite_Holder_011_strza_ka_phase_00.png"
            },
            {
              "phase": 1,
              "path": "extracted_assets\\grp\\G_REC\\sprite_holder\\00_Group.Sprite_Holder_011_strza_ka_phase_01.png",
              "url": "../extracted_assets/grp/G_REC/sprite_holder/00_Group.Sprite_Holder_011_strza_ka_phase_01.png"
            }
          ],
          "phaseCount": 2,
          "instanceOffset": 154508,
          "rect": {
            "x": 744,
            "y": 14,
            "width": 41,
            "height": 49
          },
          "geometryConfidence": "serialized_instance",
          "initialPhase": 0,
          "initiallyVisible": true,
          "draggable": false,
          "z": 8
        }
      ],
      "audio": []
    },
    {
      "id": "01_HotSpot_Holder",
      "type": "HotSpot_Holder",
      "sourceType": "Group.HotSpot_Holder",
      "namespace": "Group",
      "index": 1,
      "z": 100,
      "visible": false,
      "rect": {
        "x": 0,
        "y": -1,
        "width": 640,
        "height": 483
      },
      "geometryConfidence": "serialized_entries",
      "itemCount": null,
      "hitboxes": [
        {
          "id": 0,
          "rect": {
            "x": 629,
            "y": -1,
            "width": 11,
            "height": 483
          },
          "name": "",
          "layer": 4,
          "enabled": true,
          "flags": [
            210,
            0,
            255
          ],
          "sourceOffset": 155770,
          "geometryConfidence": "serialized_entry",
          "activeIndex": 10,
          "auxState": 0
        },
        {
          "id": 1,
          "rect": {
            "x": 0,
            "y": 6,
            "width": 635,
            "height": 474
          },
          "name": "",
          "layer": 3,
          "enabled": true,
          "flags": [
            210,
            0,
            255
          ],
          "sourceOffset": 155871,
          "geometryConfidence": "serialized_entry",
          "activeIndex": 10,
          "auxState": 0
        }
      ],
      "sourceOffset": 154648,
      "geometrySourceOffset": null,
      "privateOffset": 155759,
      "privateSize": 221,
      "primaryAssetUrl": null,
      "assets": [],
      "audio": []
    },
    {
      "id": "02_Sound_Holder",
      "type": "Sound_Holder",
      "sourceType": "Group.Sound_Holder",
      "namespace": "Group",
      "index": 2,
      "z": 0,
      "visible": false,
      "rect": {
        "x": 0,
        "y": 0,
        "width": 0,
        "height": 0
      },
      "geometryConfidence": "not_visual",
      "itemCount": null,
      "hitboxes": [],
      "sourceOffset": 155980,
      "geometrySourceOffset": null,
      "privateOffset": 156882,
      "privateSize": 2170802,
      "primaryAssetUrl": null,
      "assets": [],
      "audio": [
        {
          "kind": "WAVE",
          "path": "extracted_assets\\grp\\G_REC\\embedded\\02_Group.Sound_Holder_000_000264de.wav",
          "url": "../extracted_assets/grp/G_REC/embedded/02_Group.Sound_Holder_000_000264de.wav",
          "durationSeconds": null,
          "sampleRate": null,
          "channels": null,
          "offset": 156894,
          "id": 0
        },
        {
          "kind": "WAVE",
          "path": "extracted_assets\\grp\\G_REC\\embedded\\02_Group.Sound_Holder_001_00203492.wav",
          "url": "../extracted_assets/grp/G_REC/embedded/02_Group.Sound_Holder_001_00203492.wav",
          "durationSeconds": null,
          "sampleRate": null,
          "channels": null,
          "offset": 2110610,
          "id": 1
        },
        {
          "kind": "WAVE",
          "path": "extracted_assets\\grp\\G_REC\\embedded\\02_Group.Sound_Holder_002_002035e0.wav",
          "url": "../extracted_assets/grp/G_REC/embedded/02_Group.Sound_Holder_002_002035e0.wav",
          "durationSeconds": null,
          "sampleRate": null,
          "channels": null,
          "offset": 2110944,
          "id": 2
        },
        {
          "kind": "WAVE",
          "path": "extracted_assets\\grp\\G_REC\\embedded\\02_Group.Sound_Holder_003_00208e68.wav",
          "url": "../extracted_assets/grp/G_REC/embedded/02_Group.Sound_Holder_003_00208e68.wav",
          "durationSeconds": null,
          "sampleRate": null,
          "channels": null,
          "offset": 2133608,
          "id": 3
        },
        {
          "kind": "WAVE",
          "path": "extracted_assets\\grp\\G_REC\\embedded\\02_Group.Sound_Holder_004_0020bfe4.wav",
          "url": "../extracted_assets/grp/G_REC/embedded/02_Group.Sound_Holder_004_0020bfe4.wav",
          "durationSeconds": null,
          "sampleRate": null,
          "channels": null,
          "offset": 2146276,
          "id": 4
        },
        {
          "kind": "WAVE",
          "path": "extracted_assets\\grp\\G_REC\\embedded\\02_Group.Sound_Holder_005_0023270c.wav",
          "url": "../extracted_assets/grp/G_REC/embedded/02_Group.Sound_Holder_005_0023270c.wav",
          "durationSeconds": null,
          "sampleRate": null,
          "channels": null,
          "offset": 2303756,
          "id": 5
        },
        {
          "kind": "WAVE",
          "path": "extracted_assets\\grp\\G_REC\\embedded\\02_Group.Sound_Holder_006_002355ca.wav",
          "url": "../extracted_assets/grp/G_REC/embedded/02_Group.Sound_Holder_006_002355ca.wav",
          "durationSeconds": null,
          "sampleRate": null,
          "channels": null,
          "offset": 2315722,
          "id": 6
        }
      ]
    },
    {
      "id": "03_Bitmap_Holder",
      "type": "Bitmap_Holder",
      "sourceType": "Group.Bitmap_Holder",
      "namespace": "Group",
      "index": 3,
      "z": 0,
      "visible": true,
      "rect": {
        "x": 611,
        "y": 419,
        "width": 29,
        "height": 52
      },
      "geometryConfidence": "serialized_entries",
      "itemCount": null,
      "hitboxes": [],
      "sourceOffset": 2327684,
      "geometrySourceOffset": null,
      "privateOffset": 2328822,
      "privateSize": 1820,
      "primaryAssetUrl": "../extracted_assets/grp/G_REC/bitmap_holder/03_Group.Bitmap_Holder_000_warstawa__29x52.bmp",
      "assets": [
        {
          "kind": "bitmap_holder_bmp",
          "path": "extracted_assets\\grp\\G_REC\\bitmap_holder\\03_Group.Bitmap_Holder_000_warstawa__29x52.bmp",
          "url": "../extracted_assets/grp/G_REC/bitmap_holder/03_Group.Bitmap_Holder_000_warstawa__29x52.bmp",
          "renderPath": "extracted_assets\\grp\\G_REC\\bitmap_holder\\03_Group.Bitmap_Holder_000_warstawa__29x52.bmp",
          "stillPath": null,
          "stillUrl": null,
          "width": 29,
          "height": 52,
          "frameCount": null,
          "offset": 2328962,
          "name": "warstawa_",
          "id": 0,
          "initiallyVisible": false,
          "rect": {
            "x": 611,
            "y": 419,
            "width": 29,
            "height": 52
          },
          "geometryConfidence": "serialized_entry"
        }
      ],
      "audio": []
    }
  ],
  "warnings": []
}